{
  "as_of": "2026-06-30T16:00:00-04:00",
  "cash": 371.94,
  "total_value": 507.67254445,
  "positions": [
    {
      "symbol": "MS",
      "qty": 0.215357,
      "available_qty": 0.215357,
      "avg_price": 213.55,
      "current_price": 208.98,
      "market_value": 45.005306,
      "unrealized_pnl": -0.984181
    },
    {
      "symbol": "VRTX",
      "qty": 0.101027,
      "available_qty": 0.101027,
      "avg_price": 464.73,
      "current_price": 496.65,
      "market_value": 50.175061,
      "unrealized_pnl": 3.224783
    },
    {
      "symbol": "AXP",
      "qty": 0.119992,
      "available_qty": 0.119992,
      "avg_price": 339.61,
      "current_price": 338.2,
      "market_value": 40.581294,
      "unrealized_pnl": -0.169189
    }
  ]
}
